chibi_dl/__init__.py
chibi_dl/config.py
chibi_dl/main.py
chibi_dl/site/__init__.py
chibi_dl/site/base/__init__.py
chibi_dl/site/base/exceptions.py
chibi_dl/site/base/site.py
chibi_dl-1.0.1.dist-info/COPYING
chibi_dl-1.0.1.dist-info/METADATA
chibi_dl-1.0.1.dist-info/WHEEL
chibi_dl-1.0.1.dist-info/top_level.txt
chibi_dl-1.0.1.dist-info/RECORD
