Metadata-Version: 2.2
Name: chibi_dl
Version: 1.0.1
Author: dem4ply
Author-email: 
Classifier: Environment :: Console
Classifier: Intended Audience :: Developers
Classifier: Programming Language :: Python
License-File: COPYING
Requires-Dist: chibi>=0.11.10
Requires-Dist: chibi_requests>=0.1.1
Requires-Dist: selenium>=3.141.0
Requires-Dist: undetected-chromedriver>=3.5.2
Dynamic: author
Dynamic: classifier
Dynamic: description
Dynamic: requires-dist
